blikon_sdk/__init__.py
blikon_sdk/v2/__init__.py
blikon_sdk/v2/core/__init__.py
blikon_sdk/v2/core/core.py
blikon_sdk/v2/core/setup.py
blikon_sdk/v2/endpoints/__init__.py
blikon_sdk/v2/endpoints/token.py
blikon_sdk/v2/helpers/__init__.py
blikon_sdk/v2/helpers/msg_helper.py
blikon_sdk/v2/helpers/request_helper.py
blikon_sdk/v2/helpers/secrets_helper.py
blikon_sdk/v2/helpers/setup_logger_helper.py
blikon_sdk/v2/middleware/__init__.py
blikon_sdk/v2/middleware/error_handler.py
blikon_sdk/v2/middleware/http_logger.py
blikon_sdk/v2/models/__init__.py
blikon_sdk/v2/models/error_detail_model.py
blikon_sdk/v2/models/http_log_model.py
blikon_sdk/v2/models/sdk_client_setup_model.py
blikon_sdk/v2/models/sdk_configuration_model.py
blikon_sdk/v2/schemas/__init__.py
blikon_sdk/v2/schemas/critical_error_schemas.py
blikon_sdk/v2/schemas/shared_schemas.py
blikon_sdk/v2/services/__init__.py
blikon_sdk/v2/services/log_service.py
blikon_sdk/v2/services/security_service.py
blikon_sdk/v2/utils/__init__.py
blikon_sdk/v2/utils/utils.py
blikon_sdk/v2/validations/__init__.py
blikon_sdk/v2/validations/validations.py
blikon_sdk-2.1.0.dist-info/METADATA
blikon_sdk-2.1.0.dist-info/WHEEL
blikon_sdk-2.1.0.dist-info/top_level.txt
blikon_sdk-2.1.0.dist-info/RECORD
